traffic.v
module traffic_light(
    input clk,
    input reset,
    output reg [1:0] light,
    output reg [1:0] state,
    output reg [3:0] count
);

// State definitions
parameter RED    = 2'b00;
parameter GREEN  = 2'b01;
parameter YELLOW = 2'b10;

// FSM Logic
always @(posedge clk or posedge reset)
begin
    if(reset)
    begin
        state <= RED;
        count <= 0;
    end
    else
    begin
        count <= count + 1;

        case(state)

            RED:
            begin
                if(count == 5)
                begin
                    state <= GREEN;
                    count <= 0;
                end
            end

            GREEN:
            begin
                if(count == 5)
                begin
                    state <= YELLOW;
                    count <= 0;
                end
            end

            YELLOW:
            begin
                if(count == 2)
                begin
                    state <= RED;
                    count <= 0;
                end
            end

            default:
            begin
                state <= RED;
                count <= 0;
            end

        endcase
    end
end

// Output Logic
always @(*)
begin
    case(state)
        RED:    light = 2'b00;
        GREEN:  light = 2'b01;
        YELLOW: light = 2'b10;
        default: light = 2'b00;
    endcase
end

endmodule

traffic_tb.v
module traffic_tb;

reg clk;
reg reset;

wire [1:0] light;
wire [1:0] state;
wire [3:0] count;

// DUT
traffic_light uut (
    .clk(clk),
    .reset(reset),
    .light(light),
    .state(state),
    .count(count)
);

// Clock generation
always #5 clk = ~clk;

initial
begin

    // Waveform file
    $dumpfile("traffic.vcd");
    $dumpvars(0, traffic_tb);

    // Monitor values
    $monitor("Time=%0t Reset=%b State=%b Count=%d Light=%b",
              $time, reset, state, count, light);

    clk = 0;
    reset = 1;

    #10 reset = 0;

    #300 $finish;

end

endmodule

traffic.vcd
$date
	Sun Jun 14 13:52:44 2026
$end
$version
	Icarus Verilog
$end
$timescale
	1s
$end
$scope module traffic_tb $end
$var wire 2 ! state [1:0] $end
$var wire 2 " light [1:0] $end
$var wire 4 # count [3:0] $end
$var reg 1 $ clk $end
$var reg 1 % reset $end
$scope module uut $end
$var wire 1 $ clk $end
$var wire 1 % reset $end
$var reg 4 & count [3:0] $end
$var reg 2 ' light [1:0] $end
$var reg 2 ( state [1:0] $end
$upscope $end
$upscope $end
$enddefinitions $end
#0
$dumpvars
b0 (
b0 '
b0 &
1%
0$
b0 #
b0 "
b0 !
$end
#5
1$
#10
0$
0%
#15
b1 #
b1 &
1$
#20
0$
#25
b10 #
b10 &
1$
#30
0$
#35
b11 #
b11 &
1$
#40
0$
#45
b100 #
b100 &
1$
#50
0$
#55
b101 #
b101 &
1$
#60
0$
#65
b1 "
b1 '
b1 !
b1 (
b0 #
b0 &
1$
#70
0$
#75
b1 #
b1 &
1$
#80
0$
#85
b10 #
b10 &
1$
#90
0$
#95
b11 #
b11 &
1$
#100
0$
#105
b100 #
b100 &
1$
#110
0$
#115
b101 #
b101 &
1$
#120
0$
#125
b10 "
b10 '
b10 !
b10 (
b0 #
b0 &
1$
#130
0$
#135
b1 #
b1 &
1$
#140
0$
#145
b10 #
b10 &
1$
#150
0$
#155
b0 "
b0 '
b0 !
b0 (
b0 #
b0 &
1$
#160
0$
#165
b1 #
b1 &
1$
#170
0$
#175
b10 #
b10 &
1$
#180
0$
#185
b11 #
b11 &
1$
#190
0$
#195
b100 #
b100 &
1$
#200
0$
#205
b101 #
b101 &
1$
#210
0$
#215
b1 "
b1 '
b1 !
b1 (
b0 #
b0 &
1$
#220
0$
#225
b1 #
b1 &
1$
#230
0$
#235
b10 #
b10 &
1$
#240
0$
#245
b11 #
b11 &
1$
#250
0$
#255
b100 #
b100 &
1$
#260
0$
#265
b101 #
b101 &
1$
#270
0$
#275
b10 "
b10 '
b10 !
b10 (
b0 #
b0 &
1$
#280
0$
#285
b1 #
b1 &
1$
#290
0$
#295
b10 #
b10 &
1$
#300
0$
#305
b0 "
b0 '
b0 !
b0 (
b0 #
b0 &
1$
